girsh/__init__.py
girsh/girsh.py
girsh/py.typed
girsh/core/__init__.py
girsh/core/config.py
girsh/core/files.py
girsh/core/installed.py
girsh/core/repos.py
girsh/core/utils.py
girsh/templates/config_template.yaml
girsh-0.1.32.dist-info/METADATA
girsh-0.1.32.dist-info/WHEEL
girsh-0.1.32.dist-info/entry_points.txt
girsh-0.1.32.dist-info/licenses/LICENSE
girsh-0.1.32.dist-info/RECORD
