Metadata-Version: 2.4
Name: girsh
Version: 0.1.32
Summary: This tool downloads and installs release binaries from GitHub repositories.
Project-URL: Documentation, https://palto42.github.io/girsh/
Project-URL: Homepage, https://palto42.github.io/girsh/
Project-URL: Repository, https://github.com/palto42/girsh
Author-email: Matthias Homann <palto@mailbox.org>
License-File: LICENSE
Keywords: python
Classifier: Intended Audience :: Developers
Classifier: Programming Language :: Python
Classifier: Programming Language :: Python :: 3
Classifier: Programming Language :: Python :: 3.10
Classifier: Programming Language :: Python :: 3.11
Classifier: Programming Language :: Python :: 3.12
Classifier: Programming Language :: Python :: 3.13
Classifier: Topic :: Software Development :: Libraries :: Python Modules
Requires-Python: <4.0,>=3.10
Requires-Dist: loguru>=0.7.3
Requires-Dist: psutil>=7.0.0
Requires-Dist: pyyaml>=6.0.2
Requires-Dist: requests>=2.32.3
